modelsmith/__init__.py
modelsmith/enums.py
modelsmith/exceptions.py
modelsmith/forge.py
modelsmith/language_models.py
modelsmith/prompt.py
modelsmith/response_model.py
modelsmith/utilities.py
modelsmith-0.7.0.dist-info/WHEEL
modelsmith-0.7.0.dist-info/METADATA
modelsmith-0.7.0.dist-info/RECORD
