Metadata-Version: 2.4
Name: modelsmith
Version: 0.7.0
Summary: Get Pydantic models and Python types as LLM responses from Anthropic, Google Vertex AI, and OpenAI models.
Keywords: anthropic,openai,vertexai,pydantic,models,types,llm
Author: Christo Olivier
Author-email: Christo Olivier <mail@christoolivier.com>
License-Expression: MIT
Requires-Dist: google-genai>=1.36.0
Requires-Dist: anthropic>=0.67.0
Requires-Dist: openai>=1.107.2
Requires-Dist: jinja2>=3.1.6
Requires-Dist: pydantic>=2.11.9
Requires-Dist: tenacity>=9.1.2
Maintainer: Christo Olivier
Maintainer-email: Christo Olivier <mail@christoolivier.com>
Requires-Python: ~=3.10.0
Project-URL: Documentation, https://christo-olivier.github.io/modelsmith
Project-URL: Homepage, https://github.com/christo-olivier/modelsmith
Project-URL: Repository, https://github.com/christo-olivier/modelsmith
